groupdocs_signature_cloud/__init__.py
groupdocs_signature_cloud/api_client.py
groupdocs_signature_cloud/api_exception.py
groupdocs_signature_cloud/auth.py
groupdocs_signature_cloud/configuration.py
groupdocs_signature_cloud/rest.py
groupdocs_signature_cloud/apis/__init__.py
groupdocs_signature_cloud/apis/file_api.py
groupdocs_signature_cloud/apis/folder_api.py
groupdocs_signature_cloud/apis/info_api.py
groupdocs_signature_cloud/apis/license_api.py
groupdocs_signature_cloud/apis/preview_api.py
groupdocs_signature_cloud/apis/sign_api.py
groupdocs_signature_cloud/apis/storage_api.py
groupdocs_signature_cloud/models/__init__.py
groupdocs_signature_cloud/models/api_error.py
groupdocs_signature_cloud/models/api_error_response.py
groupdocs_signature_cloud/models/barcode_signature.py
groupdocs_signature_cloud/models/barcode_type.py
groupdocs_signature_cloud/models/barcodes_result.py
groupdocs_signature_cloud/models/base_settings.py
groupdocs_signature_cloud/models/border_line.py
groupdocs_signature_cloud/models/brush.py
groupdocs_signature_cloud/models/checkbox_form_field_signature.py
groupdocs_signature_cloud/models/color.py
groupdocs_signature_cloud/models/combobox_form_field_signature.py
groupdocs_signature_cloud/models/consumption_result.py
groupdocs_signature_cloud/models/delete_options.py
groupdocs_signature_cloud/models/delete_result.py
groupdocs_signature_cloud/models/delete_settings.py
groupdocs_signature_cloud/models/digital_form_field_signature.py
groupdocs_signature_cloud/models/digital_signature.py
groupdocs_signature_cloud/models/digital_signature_appearance.py
groupdocs_signature_cloud/models/digital_vba.py
groupdocs_signature_cloud/models/disc_usage.py
groupdocs_signature_cloud/models/error.py
groupdocs_signature_cloud/models/error_details.py
groupdocs_signature_cloud/models/file_info.py
groupdocs_signature_cloud/models/file_version.py
groupdocs_signature_cloud/models/file_versions.py
groupdocs_signature_cloud/models/files_list.py
groupdocs_signature_cloud-25.6.dist-info/licenses/LICENSE
groupdocs_signature_cloud-25.6.dist-info/METADATA
groupdocs_signature_cloud-25.6.dist-info/WHEEL
groupdocs_signature_cloud-25.6.dist-info/top_level.txt
groupdocs_signature_cloud-25.6.dist-info/RECORD
